treezy/__init__.py
treezy/bitset.py
treezy/newick.py
treezy/nexus.py
treezy/node.py
treezy/tree.py
treezy/treeio.py
treezy-0.0.1.dist-info/licenses/LICENSE
treezy-0.0.1.dist-info/METADATA
treezy-0.0.1.dist-info/WHEEL
treezy-0.0.1.dist-info/top_level.txt
treezy-0.0.1.dist-info/RECORD
