Metadata-Version: 2.4
Name: treezy
Version: 0.0.1
Summary: Simple library for manipulating phylogenetic trees
Author-email: Mathieu Fourment <mathieu.fourment@uts.edu.au>
License-Expression: MIT
Project-URL: homepage, https://github.com/4ment/treezy
Project-URL: repository, https://github.com/4ment/treezy
Keywords: bioinformatics,phylogenetics,tree
Classifier: Intended Audience :: Science/Research
Classifier: Operating System :: OS Independent
Classifier: Programming Language :: Python :: 3.9
Classifier: Programming Language :: Python :: 3.10
Classifier: Programming Language :: Python :: 3.11
Classifier: Programming Language :: Python :: 3.12
Classifier: Programming Language :: Python :: 3.13
Classifier: Topic :: Scientific/Engineering :: Bio-Informatics
Requires-Python: >=3.9
License-File: LICENSE
Dynamic: license-file
